{
    "netbird": {
        "cargoLocks": null,
        "date": null,
        "extract": null,
        "name": "netbird",
        "passthru": {
            "vendorHash": "sha256-JMynPCH5Zvzz8nYI7DPu9TzU+rWJemPwyDdlPkFiqds="
        },
        "pinned": false,
        "src": {
            "deepClone": false,
            "fetchSubmodules": false,
            "leaveDotGit": false,
            "name": null,
            "owner": "netbirdio",
            "repo": "netbird",
            "rev": "v0.59.6",
            "sha256": "sha256-WCzC6T2FqbdSjedvPK223zLE3rYuKUCec8BEkNK/sPg=",
            "sparseCheckout": [],
            "type": "github"
        },
        "version": "v0.59.6"
    }
}