{
    "netbird": {
        "cargoLocks": null,
        "date": null,
        "extract": null,
        "name": "netbird",
        "passthru": {
            "vendorHash": "sha256-ZjeTKj99BTSNFOvtywfmuXfYVxU3s9O2EwD/4IZodvs="
        },
        "pinned": false,
        "src": {
            "deepClone": false,
            "fetchSubmodules": false,
            "leaveDotGit": false,
            "name": null,
            "owner": "netbirdio",
            "repo": "netbird",
            "rev": "v0.58.2",
            "sha256": "sha256-rl3nO/EZ9eB63LAPRMz7wKQZIVPnI9ymDuFylIds7q4=",
            "sparseCheckout": [],
            "type": "github"
        },
        "version": "v0.58.2"
    }
}